LICENSE
MANIFEST.in
README.md
setup.cfg
setup.py
preset_sqlalchemy_dremio.egg-info/PKG-INFO
preset_sqlalchemy_dremio.egg-info/SOURCES.txt
preset_sqlalchemy_dremio.egg-info/dependency_links.txt
preset_sqlalchemy_dremio.egg-info/entry_points.txt
preset_sqlalchemy_dremio.egg-info/not-zip-safe
preset_sqlalchemy_dremio.egg-info/requires.txt
preset_sqlalchemy_dremio.egg-info/top_level.txt
sqlalchemy_dremio/__init__.py
sqlalchemy_dremio/base.py
sqlalchemy_dremio/db.py
sqlalchemy_dremio/exceptions.py
sqlalchemy_dremio/flight.py
sqlalchemy_dremio/flight_auth.py
sqlalchemy_dremio/pyodbc.py
sqlalchemy_dremio/query.py
test/test_dremio.py