Metadata-Version: 2.1
Name: preset-sqlalchemy-dremio
Version: 1.2.1
Summary: Fork of sqlalchemy-dremio 1.2.1 for parallel deployment with newer versions
Home-page: https://github.com/narendrans/sqlalchemy_dremio
Author: Naren
Author-email: me@narendran.info
License: Apache Software License
Keywords: sqlalchemy_dremio
Classifier: Development Status :: 5 - Production/Stable
Classifier: Intended Audience :: Developers
Classifier: License :: OSI Approved :: Apache Software License
Classifier: Natural Language :: English
Classifier: Programming Language :: Python :: 3
Classifier: Programming Language :: Python :: 3.7
License-File: LICENSE
